eh_extract/__init__.py
eh_extract/cli.py
eh_extract-1.1.1.dist-info/licenses/LICENSE
eh_extract-1.1.1.dist-info/METADATA
eh_extract-1.1.1.dist-info/WHEEL
eh_extract-1.1.1.dist-info/entry_points.txt
eh_extract-1.1.1.dist-info/top_level.txt
eh_extract-1.1.1.dist-info/RECORD
