Metadata-Version: 2.4
Name: eh-extract
Version: 1.1.1
Summary: A CLI tool to extract file contents and structure into a single text file.
Home-page: https://github.com/EsmailEbrahim/eh-extract-files-to-txt
Author: Esmail Ebrahim Hamza
Author-email: Esmail Ebrahim Hamza <esmailebraheem771@gmail.com>
License: MIT
Project-URL: Homepage, https://github.com/EsmailEbrahim/eh-extract-files-to-txt
Keywords: cli,file-extraction,codebase,utility
Classifier: Programming Language :: Python :: 3
Classifier: License :: OSI Approved :: MIT License
Classifier: Operating System :: OS Independent
Requires-Python: >=3.7
License-File: LICENSE
Dynamic: license-file
